dsnrun/__init__.py
dsnrun/argv.py
dsnrun/fail.py
dsnrun/namemain.py
dsnrun/scmversion.py
dsnrun/tests.py
dsnrun/scripts/__init__.py
dsnrun/scripts/dsnrun.py
dsnrun-0.2.0.dist-info/licenses/LICENSE
dsnrun-0.2.0.dist-info/METADATA
dsnrun-0.2.0.dist-info/WHEEL
dsnrun-0.2.0.dist-info/entry_points.txt
dsnrun-0.2.0.dist-info/top_level.txt
dsnrun-0.2.0.dist-info/RECORD
