Metadata-Version: 2.4
Name: dsnrun
Version: 0.2.0
Summary: Run arbirary scripts with sentry_sdk initialized to some DSN on the fly
Author-email: "Bugsink B.V." <info@bugsink.com>
License-Expression: BSD-3-Clause
Project-URL: repository, https://github.com/bugsink/dsnrun/
Project-URL: issues, https://github.com/bugsink/dsnrun/issues
Classifier: Programming Language :: Python :: 3
Requires-Python: >=3.8
License-File: LICENSE
Requires-Dist: sentry_sdk
Dynamic: license-file
